<?xml version="1.0" encoding="utf-8"?>
<CMSDDocument xmlns:xsd="http://www.w3.org/2001/XMLSchema" xmlns:xsi="http://www.w3.org/2001/XMLSchema-instance">
  <HeaderSection>
    <DocumentIdentifier>4.2 - Machine Tending using Feeler Machines</DocumentIdentifier>
    <Description>Export from Visual Components. Copyright: UGent ISyE.</Description>
    <Version>4.8</Version>
    <CreationTime>3/8/2024 10:46:36 AM</CreationTime>
    <Metadata>
      <PropertyDescription>
        <PropertyDescription>
          <Name>Author</Name>
          <Description>Jiaqi Zhao</Description>
          <ParentEntityName>Layout</ParentEntityName>
          <UnitType>AreaUnit</UnitType>
        </PropertyDescription>
        <PropertyDescription>
          <Name>Email</Name>
          <Description>Jiaqi.Zhao@UGent.be</Description>
          <ParentEntityName>Layout</ParentEntityName>
          <UnitType>AreaUnit</UnitType>
        </PropertyDescription>
        <PropertyDescription>
          <Name>Website</Name>
          <Description>https://telefoonboek.ugent.be/nl/people/000191362105</Description>
          <ParentEntityName>Layout</ParentEntityName>
          <UnitType>AreaUnit</UnitType>
        </PropertyDescription>
      </PropertyDescription>
    </Metadata>
    <UnitDefaults>
      <AreaUnit>squareInch</AreaUnit>
      <LengthUnit>millimeter</LengthUnit>
      <PowerUnit>horsepower</PowerUnit>
      <SpeedUnit>footPerSecond</SpeedUnit>
      <TemperatureUnit>Celsius</TemperatureUnit>
      <TimeUnit>second</TimeUnit>
      <VolumeUnit>cubicCentimeter</VolumeUnit>
      <WeightUnit>ounce</WeightUnit>
    </UnitDefaults>
  </HeaderSection>
  <DataSection>
    <Layout>
      <Identifier>4.2 - Machine Tending using Feeler Machines</Identifier>
      <Description>UGent ISyE Visual Components model</Description>
      <Name>4.2 - Machine Tending using Feeler Machines</Name>
      <Boundary>
        <Width>4728.118</Width>
        <Depth>9260.996</Depth>
        <Height>2337.1</Height>
        <Unit>millimeter</Unit>
        <CoordinateSystem>centerBased</CoordinateSystem>
      </Boundary>
      <Placement>
        <LayoutElementIdentifier>LayoutObject:Conveyor_5</LayoutElementIdentifier>
        <Location>
          <X>3446.087</X>
          <Y>492.755</Y>
          <Z>0</Z>
        </Location>
        <Transformations>
          <Rotation>
            <XDegree>0</XDegree>
            <YDegree>0</YDegree>
            <ZDegree>90</ZDegree>
          </Rotation>
          <Translation>
            <XOffset>3446.087</XOffset>
            <YOffset>492.755</YOffset>
            <ZOffset>0</ZOffset>
          </Translation>
          <Scaling>
            <XPercent>1</XPercent>
            <YPercent>1</YPercent>
            <ZPercent>1</ZPercent>
          </Scaling>
        </Transformations>
      </Placement>
      <Placement>
        <LayoutElementIdentifier>LayoutObject:Conveyor_4</LayoutElementIdentifier>
        <Location>
          <X>3446.088</X>
          <Y>-1008.245</Y>
          <Z>0</Z>
        </Location>
        <Transformations>
          <Rotation>
            <XDegree>0</XDegree>
            <YDegree>0</YDegree>
            <ZDegree>90</ZDegree>
          </Rotation>
          <Translation>
            <XOffset>3446.088</XOffset>
            <YOffset>-1008.245</YOffset>
            <ZOffset>0</ZOffset>
          </Translation>
          <Scaling>
            <XPercent>1</XPercent>
            <YPercent>1</YPercent>
            <ZPercent>1</ZPercent>
          </Scaling>
        </Transformations>
      </Placement>
      <Placement>
        <LayoutElementIdentifier>LayoutObject:Conveyor_3</LayoutElementIdentifier>
        <Location>
          <X>3446.089</X>
          <Y>-2509.245</Y>
          <Z>0</Z>
        </Location>
        <Transformations>
          <Rotation>
            <XDegree>0</XDegree>
            <YDegree>0</YDegree>
            <ZDegree>90</ZDegree>
          </Rotation>
          <Translation>
            <XOffset>3446.089</XOffset>
            <YOffset>-2509.245</YOffset>
            <ZOffset>0</ZOffset>
          </Translation>
          <Scaling>
            <XPercent>1</XPercent>
            <YPercent>1</YPercent>
            <ZPercent>1</ZPercent>
          </Scaling>
        </Transformations>
      </Placement>
      <Placement>
        <LayoutElementIdentifier>LayoutObject:Conveyor</LayoutElementIdentifier>
        <Location>
          <X>0</X>
          <Y>0</Y>
          <Z>0</Z>
        </Location>
        <Transformations>
          <Rotation>
            <XDegree>0</XDegree>
            <YDegree>0</YDegree>
            <ZDegree>0</ZDegree>
          </Rotation>
          <Translation>
            <XOffset>0</XOffset>
            <YOffset>0</YOffset>
            <ZOffset>0</ZOffset>
          </Translation>
          <Scaling>
            <XPercent>1</XPercent>
            <YPercent>1</YPercent>
            <ZPercent>1</ZPercent>
          </Scaling>
        </Transformations>
      </Placement>
      <Placement>
        <LayoutElementIdentifier>LayoutObject:Curve_Conveyor</LayoutElementIdentifier>
        <Location>
          <X>2001</X>
          <Y>0</Y>
          <Z>0</Z>
        </Location>
        <Transformations>
          <Rotation>
            <XDegree>0</XDegree>
            <YDegree>0</YDegree>
            <ZDegree>0</ZDegree>
          </Rotation>
          <Translation>
            <XOffset>2001</XOffset>
            <YOffset>0</YOffset>
            <ZOffset>0</ZOffset>
          </Translation>
          <Scaling>
            <XPercent>1</XPercent>
            <YPercent>1</YPercent>
            <ZPercent>1</ZPercent>
          </Scaling>
        </Transformations>
      </Placement>
      <Placement>
        <LayoutElementIdentifier>LayoutObject:Conveyor_2</LayoutElementIdentifier>
        <Location>
          <X>3001</X>
          <Y>-1000</Y>
          <Z>0</Z>
        </Location>
        <Transformations>
          <Rotation>
            <XDegree>0</XDegree>
            <YDegree>0</YDegree>
            <ZDegree>-90</ZDegree>
          </Rotation>
          <Translation>
            <XOffset>3001</XOffset>
            <YOffset>-1000</YOffset>
            <ZOffset>0</ZOffset>
          </Translation>
          <Scaling>
            <XPercent>1</XPercent>
            <YPercent>1</YPercent>
            <ZPercent>1</ZPercent>
          </Scaling>
        </Transformations>
      </Placement>
      <Placement>
        <LayoutElementIdentifier>LayoutObject:Product_Feeder</LayoutElementIdentifier>
        <Location>
          <X>-150</X>
          <Y>0</Y>
          <Z>0</Z>
        </Location>
        <Transformations>
          <Rotation>
            <XDegree>0</XDegree>
            <YDegree>0</YDegree>
            <ZDegree>0</ZDegree>
          </Rotation>
          <Translation>
            <XOffset>-150</XOffset>
            <YOffset>0</YOffset>
            <ZOffset>0</ZOffset>
          </Translation>
          <Scaling>
            <XPercent>1</XPercent>
            <YPercent>1</YPercent>
            <ZPercent>1</ZPercent>
          </Scaling>
        </Transformations>
      </Placement>
      <Placement>
        <LayoutElementIdentifier>LayoutObject:From_Conveyor_Process</LayoutElementIdentifier>
        <Location>
          <X>3001</X>
          <Y>-2511</Y>
          <Z>0</Z>
        </Location>
        <Transformations>
          <Rotation>
            <XDegree>0</XDegree>
            <YDegree>0</YDegree>
            <ZDegree>-90</ZDegree>
          </Rotation>
          <Translation>
            <XOffset>3001</XOffset>
            <YOffset>-2511</YOffset>
            <ZOffset>0</ZOffset>
          </Translation>
          <Scaling>
            <XPercent>1</XPercent>
            <YPercent>1</YPercent>
            <ZPercent>1</ZPercent>
          </Scaling>
        </Transformations>
      </Placement>
      <Placement>
        <LayoutElementIdentifier>LayoutObject:To_Conveyor_Process</LayoutElementIdentifier>
        <Location>
          <X>3446.089</X>
          <Y>-2519.245</Y>
          <Z>0</Z>
        </Location>
        <Transformations>
          <Rotation>
            <XDegree>0</XDegree>
            <YDegree>0</YDegree>
            <ZDegree>90</ZDegree>
          </Rotation>
          <Translation>
            <XOffset>3446.089</XOffset>
            <YOffset>-2519.245</YOffset>
            <ZOffset>0</ZOffset>
          </Translation>
          <Scaling>
            <XPercent>1</XPercent>
            <YPercent>1</YPercent>
            <ZPercent>1</ZPercent>
          </Scaling>
        </Transformations>
      </Placement>
      <Placement>
        <LayoutElementIdentifier>LayoutObject:RobotController</LayoutElementIdentifier>
        <Location>
          <X>3279.918</X>
          <Y>-3462.837</Y>
          <Z>0</Z>
        </Location>
        <Transformations>
          <Rotation>
            <XDegree>0</XDegree>
            <YDegree>0</YDegree>
            <ZDegree>0</ZDegree>
          </Rotation>
          <Translation>
            <XOffset>3279.918</XOffset>
            <YOffset>-3462.837</YOffset>
            <ZOffset>0</ZOffset>
          </Translation>
          <Scaling>
            <XPercent>1</XPercent>
            <YPercent>1</YPercent>
            <ZPercent>1</ZPercent>
          </Scaling>
        </Transformations>
      </Placement>
      <Placement>
        <LayoutElementIdentifier>LayoutObject:EH320</LayoutElementIdentifier>
        <Location>
          <X>3932.139</X>
          <Y>-4351.178</Y>
          <Z>0</Z>
        </Location>
        <Transformations>
          <Rotation>
            <XDegree>0</XDegree>
            <YDegree>0</YDegree>
            <ZDegree>0</ZDegree>
          </Rotation>
          <Translation>
            <XOffset>3932.139</XOffset>
            <YOffset>-4351.178</YOffset>
            <ZOffset>0</ZOffset>
          </Translation>
          <Scaling>
            <XPercent>1</XPercent>
            <YPercent>1</YPercent>
            <ZPercent>1</ZPercent>
          </Scaling>
        </Transformations>
      </Placement>
    </Layout>
    <Resource>
      <Identifier>Resource:4.2_-_Machine_Tending_using_Feeler_Machines</Identifier>
      <Description>4.2_-_Machine_Tending_using_Feeler_Machines</Description>
      <ResourceType>other</ResourceType>
      <Name>4.2_-_Machine_Tending_using_Feeler_Machines</Name>
      <CurrentStatus>busy</CurrentStatus>
      <GroupDefinition>
        <ResourceGroupMember>
          <ResourceIdentifier>Resource:Conveyor_5</ResourceIdentifier>
        </ResourceGroupMember>
        <ResourceGroupMember>
          <ResourceIdentifier>Resource:Conveyor_4</ResourceIdentifier>
        </ResourceGroupMember>
        <ResourceGroupMember>
          <ResourceIdentifier>Resource:Conveyor_3</ResourceIdentifier>
        </ResourceGroupMember>
        <ResourceGroupMember>
          <ResourceIdentifier>Resource:Conveyor</ResourceIdentifier>
        </ResourceGroupMember>
        <ResourceGroupMember>
          <ResourceIdentifier>Resource:Curve_Conveyor</ResourceIdentifier>
        </ResourceGroupMember>
        <ResourceGroupMember>
          <ResourceIdentifier>Resource:Conveyor_2</ResourceIdentifier>
        </ResourceGroupMember>
        <ResourceGroupMember>
          <ResourceIdentifier>Resource:Product_Feeder</ResourceIdentifier>
        </ResourceGroupMember>
        <ResourceGroupMember>
          <ResourceIdentifier>Resource:From_Conveyor_Process</ResourceIdentifier>
        </ResourceGroupMember>
        <ResourceGroupMember>
          <ResourceIdentifier>Resource:To_Conveyor_Process</ResourceIdentifier>
        </ResourceGroupMember>
        <ResourceGroupMember>
          <ResourceIdentifier>Resource:RobotController</ResourceIdentifier>
        </ResourceGroupMember>
        <ResourceGroupMember>
          <ResourceIdentifier>Resource:EH320</ResourceIdentifier>
        </ResourceGroupMember>
        <Connection>
          <Identifier>Connection:Conveyor_4-Conveyor_5</Identifier>
          <Property>
            <Name>FromFrame</Name>
            <Unit>millimeter</Unit>
            <Value>0;1;0;0;-1;0;0;0;0;0;1;0;3446.087;492.755;700;1</Value>
          </Property>
          <Property>
            <Name>ToFrame</Name>
            <Unit>millimeter</Unit>
            <Value>0;1;0;0;-1;0;0;0;0;0;1;0;3446.087;492.755;700;1</Value>
          </Property>
          <FromResource>
            <ResourceIdentifier>Resource:Conveyor_4</ResourceIdentifier>
          </FromResource>
          <ToResource>
            <ResourceIdentifier>Resource:Conveyor_5</ResourceIdentifier>
          </ToResource>
        </Connection>
        <Connection>
          <Identifier>Connection:Conveyor_3-Conveyor_4</Identifier>
          <Property>
            <Name>FromFrame</Name>
            <Unit>millimeter</Unit>
            <Value>0;1;0;0;-1;0;0;0;0;0;1;0;3446.088;-1008.245;700;1</Value>
          </Property>
          <Property>
            <Name>ToFrame</Name>
            <Unit>millimeter</Unit>
            <Value>0;1;0;0;-1;0;0;0;0;0;1;0;3446.088;-1008.245;700;1</Value>
          </Property>
          <FromResource>
            <ResourceIdentifier>Resource:Conveyor_3</ResourceIdentifier>
          </FromResource>
          <ToResource>
            <ResourceIdentifier>Resource:Conveyor_4</ResourceIdentifier>
          </ToResource>
        </Connection>
        <Connection>
          <Identifier>Connection:Conveyor-Curve_Conveyor</Identifier>
          <Property>
            <Name>FromFrame</Name>
            <Unit>millimeter</Unit>
            <Value>1;0;0;0;0;1;0;0;0;0;1;0;2001;0;700;1</Value>
          </Property>
          <Property>
            <Name>ToFrame</Name>
            <Unit>millimeter</Unit>
            <Value>1;0;0;0;0;1;0;0;0;0;1;0;2001;0;700;1</Value>
          </Property>
          <FromResource>
            <ResourceIdentifier>Resource:Conveyor</ResourceIdentifier>
          </FromResource>
          <ToResource>
            <ResourceIdentifier>Resource:Curve_Conveyor</ResourceIdentifier>
          </ToResource>
        </Connection>
        <Connection>
          <Identifier>Connection:Curve_Conveyor-Conveyor_2</Identifier>
          <Property>
            <Name>FromFrame</Name>
            <Unit>millimeter</Unit>
            <Value>0;-1;0;0;1;0;0;0;0;0;1;0;3001;-1000;700;1</Value>
          </Property>
          <Property>
            <Name>ToFrame</Name>
            <Unit>millimeter</Unit>
            <Value>0;-1;0;0;1;0;0;0;0;0;1;0;3001;-1000;700;1</Value>
          </Property>
          <FromResource>
            <ResourceIdentifier>Resource:Curve_Conveyor</ResourceIdentifier>
          </FromResource>
          <ToResource>
            <ResourceIdentifier>Resource:Conveyor_2</ResourceIdentifier>
          </ToResource>
        </Connection>
        <Connection>
          <Identifier>Connection:Conveyor_2-From_Conveyor_Process</Identifier>
          <Property>
            <Name>FromFrame</Name>
            <Unit>millimeter</Unit>
            <Value>0;-1;0;0;1;0;0;0;0;0;1;0;3001;-2501;700;1</Value>
          </Property>
          <Property>
            <Name>ToFrame</Name>
            <Unit>millimeter</Unit>
            <Value>0;-1;0;0;1;0;0;0;0;0;1;0;3001;-2501;700;1</Value>
          </Property>
          <FromResource>
            <ResourceIdentifier>Resource:Conveyor_2</ResourceIdentifier>
          </FromResource>
          <ToResource>
            <ResourceIdentifier>Resource:From_Conveyor_Process</ResourceIdentifier>
          </ToResource>
        </Connection>
        <Connection>
          <Identifier>Connection:Product_Feeder-Conveyor</Identifier>
          <Property>
            <Name>FromFrame</Name>
            <Unit>millimeter</Unit>
            <Value>1;0;0;0;0;1;0;0;0;0;1;0;0;0;700;1</Value>
          </Property>
          <Property>
            <Name>ToFrame</Name>
            <Unit>millimeter</Unit>
            <Value>1;0;0;0;0;1;0;0;0;0;1;0;0;0;700;1</Value>
          </Property>
          <FromResource>
            <ResourceIdentifier>Resource:Product_Feeder</ResourceIdentifier>
          </FromResource>
          <ToResource>
            <ResourceIdentifier>Resource:Conveyor</ResourceIdentifier>
          </ToResource>
        </Connection>
        <Connection>
          <Identifier>Connection:To_Conveyor_Process-Conveyor_3</Identifier>
          <Property>
            <Name>FromFrame</Name>
            <Unit>millimeter</Unit>
            <Value>0;1;0;0;-1;0;0;0;0;0;1;0;3446.089;-2509.245;700;1</Value>
          </Property>
          <Property>
            <Name>ToFrame</Name>
            <Unit>millimeter</Unit>
            <Value>0;1;0;0;-1;0;0;0;0;0;1;0;3446.089;-2509.245;700;1</Value>
          </Property>
          <FromResource>
            <ResourceIdentifier>Resource:To_Conveyor_Process</ResourceIdentifier>
          </FromResource>
          <ToResource>
            <ResourceIdentifier>Resource:Conveyor_3</ResourceIdentifier>
          </ToResource>
        </Connection>
        <Connection>
          <Identifier>Connection:EH320-To_Conveyor_Process</Identifier>
          <Property>
            <Name>FromFrame</Name>
            <Unit>millimeter</Unit>
            <Value>0;1;0;0;-1;0;0;0;0;0;1;0;3952.748;-172.095;1134.4;1</Value>
          </Property>
          <Property>
            <Name>ToFrame</Name>
            <Unit>millimeter</Unit>
            <Value>0;1;0;0;-1;0;0;0;0;0;1;0;3446.087;492.755;700;1</Value>
          </Property>
          <FromResource>
            <ResourceIdentifier>Resource:EH320</ResourceIdentifier>
          </FromResource>
          <ToResource>
            <ResourceIdentifier>Resource:To_Conveyor_Process</ResourceIdentifier>
          </ToResource>
        </Connection>
        <Connection>
          <Identifier>Connection:From_Conveyor_Process-EH320</Identifier>
          <Property>
            <Name>FromFrame</Name>
            <Unit>millimeter</Unit>
            <Value>0;1;0;0;-1;0;0;0;0;0;1;0;3446.088;-1008.245;700;1</Value>
          </Property>
          <Property>
            <Name>ToFrame</Name>
            <Unit>millimeter</Unit>
            <Value>0;1;0;0;-1;0;0;0;0;0;1;0;3952.749;-1673.095;1134.4;1</Value>
          </Property>
          <FromResource>
            <ResourceIdentifier>Resource:From_Conveyor_Process</ResourceIdentifier>
          </FromResource>
          <ToResource>
            <ResourceIdentifier>Resource:EH320</ResourceIdentifier>
          </ToResource>
        </Connection>
      </GroupDefinition>
    </Resource>
    <Job>
      <Identifier>Job1</Identifier>
      <Description>Job1</Description>
      <Status>released</Status>
      <SubJob>
        <JobIdentifier>Job1:Conveyor_5</JobIdentifier>
      </SubJob>
      <SubJob>
        <JobIdentifier>Job1:Conveyor_4</JobIdentifier>
      </SubJob>
      <SubJob>
        <JobIdentifier>Job1:Conveyor_3</JobIdentifier>
      </SubJob>
      <SubJob>
        <JobIdentifier>Job1:Conveyor</JobIdentifier>
      </SubJob>
      <SubJob>
        <JobIdentifier>Job1:Curve_Conveyor</JobIdentifier>
      </SubJob>
      <SubJob>
        <JobIdentifier>Job1:Conveyor_2</JobIdentifier>
      </SubJob>
      <SubJob>
        <JobIdentifier>Job1:Product_Feeder</JobIdentifier>
      </SubJob>
      <SubJob>
        <JobIdentifier>Job1:From_Conveyor_Process</JobIdentifier>
      </SubJob>
      <SubJob>
        <JobIdentifier>Job1:To_Conveyor_Process</JobIdentifier>
      </SubJob>
      <SubJob>
        <JobIdentifier>Job1:EH320</JobIdentifier>
      </SubJob>
      <SubJob>
        <JobIdentifier>Job1:Transport:EH320-To_Conveyor_Process</JobIdentifier>
      </SubJob>
      <SubJob>
        <JobIdentifier>Job1:Transport:From_Conveyor_Process-EH320</JobIdentifier>
      </SubJob>
      <PlannedEffort>
        <SetupTime>
          <Unit>second</Unit>
          <Value>0</Value>
        </SetupTime>
        <ProcessingTime>
          <Unit>second</Unit>
          <Value>451.863</Value>
        </ProcessingTime>
      </PlannedEffort>
    </Job>
    <LayoutObject>
      <Identifier>LayoutObject:Conveyor_5</Identifier>
      <Description>Inline components. Straight conveyor.</Description>
      <Name>Conveyor_5</Name>
      <AssociatedResource>
        <ResourceIdentifier>Resource:Conveyor_5</ResourceIdentifier>
      </AssociatedResource>
      <Boundary>
        <Width>1507.544</Width>
        <Depth>376</Depth>
        <Height>700.1</Height>
        <Unit>millimeter</Unit>
        <CoordinateSystem>centerBased</CoordinateSystem>
      </Boundary>
      <Type>conveyor</Type>
      <Shape>
        <ShapeType>graphic</ShapeType>
        <Graphic>
          <GraphicType>modelGraphic</GraphicType>
          <FileName>\models\Conveyor_5.dae</FileName>
          <FileType>.dae</FileType>
          <Property>
            <Name>Up_Axis</Name>
            <Value>Z_UP</Value>
          </Property>
          <ModelUnit>millimeter</ModelUnit>
        </Graphic>
      </Shape>
    </LayoutObject>
    <Resource>
      <Identifier>Resource:Conveyor_5</Identifier>
      <Description>Conveyor_5</Description>
      <Property>
        <Name>PathCapacity</Name>
        <Value>9999</Value>
      </Property>
      <Property>
        <Name>ConveyorSpeed</Name>
        <Unit>millimeterPerSecond</Unit>
        <Value>30</Value>
      </Property>
      <Property>
        <Name>PathFrame_0</Name>
        <Description>Start</Description>
        <Unit>millimeter</Unit>
        <Value>0;1;0;0;-1;0;0;0;0;0;1;0;3446.087;492.755;700;1</Value>
      </Property>
      <Property>
        <Name>PathFrame_1</Name>
        <Description>End</Description>
        <Unit>millimeter</Unit>
        <Value>0;1;0;0;-1;0;0;0;0;0;1;0;3446.086;1993.755;700;1</Value>
      </Property>
      <ResourceType>conveyor</ResourceType>
      <Name>Conveyor_5</Name>
      <CurrentStatus>busy</CurrentStatus>
    </Resource>
    <Job>
      <Identifier>Job1:Conveyor_5</Identifier>
      <Description>Conveyor_5</Description>
      <Status>released</Status>
      <PlannedEffort>
        <ResourcesRequired>
          <Resource>
            <ResourceIdentifier>Resource:Conveyor_5</ResourceIdentifier>
          </Resource>
        </ResourcesRequired>
        <SetupTime>
          <Unit>second</Unit>
          <Value>0</Value>
        </SetupTime>
        <ProcessingTime>
          <Unit>second</Unit>
          <Value>50.033</Value>
        </ProcessingTime>
      </PlannedEffort>
    </Job>
    <LayoutObject>
      <Identifier>LayoutObject:Conveyor_4</Identifier>
      <Description>Inline components. Straight conveyor.</Description>
      <Name>Conveyor_4</Name>
      <AssociatedResource>
        <ResourceIdentifier>Resource:Conveyor_4</ResourceIdentifier>
      </AssociatedResource>
      <Boundary>
        <Width>1507.544</Width>
        <Depth>376</Depth>
        <Height>700.1</Height>
        <Unit>millimeter</Unit>
        <CoordinateSystem>centerBased</CoordinateSystem>
      </Boundary>
      <Type>conveyor</Type>
      <Shape>
        <ShapeType>graphic</ShapeType>
        <Graphic>
          <GraphicType>modelGraphic</GraphicType>
          <FileName>\models\Conveyor_4.dae</FileName>
          <FileType>.dae</FileType>
          <Property>
            <Name>Up_Axis</Name>
            <Value>Z_UP</Value>
          </Property>
          <ModelUnit>millimeter</ModelUnit>
        </Graphic>
      </Shape>
    </LayoutObject>
    <Resource>
      <Identifier>Resource:Conveyor_4</Identifier>
      <Description>Conveyor_4</Description>
      <Property>
        <Name>PathCapacity</Name>
        <Value>9999</Value>
      </Property>
      <Property>
        <Name>ConveyorSpeed</Name>
        <Unit>millimeterPerSecond</Unit>
        <Value>30</Value>
      </Property>
      <Property>
        <Name>PathFrame_0</Name>
        <Description>Start</Description>
        <Unit>millimeter</Unit>
        <Value>0;1;0;0;-1;0;0;0;0;0;1;0;3446.088;-1008.245;700;1</Value>
      </Property>
      <Property>
        <Name>PathFrame_1</Name>
        <Description>End</Description>
        <Unit>millimeter</Unit>
        <Value>0;1;0;0;-1;0;0;0;0;0;1;0;3446.087;492.755;700;1</Value>
      </Property>
      <ResourceType>conveyor</ResourceType>
      <Name>Conveyor_4</Name>
      <CurrentStatus>busy</CurrentStatus>
    </Resource>
    <Job>
      <Identifier>Job1:Conveyor_4</Identifier>
      <Description>Conveyor_4</Description>
      <Status>released</Status>
      <PlannedEffort>
        <ResourcesRequired>
          <Resource>
            <ResourceIdentifier>Resource:Conveyor_4</ResourceIdentifier>
          </Resource>
        </ResourcesRequired>
        <SetupTime>
          <Unit>second</Unit>
          <Value>0</Value>
        </SetupTime>
        <ProcessingTime>
          <Unit>second</Unit>
          <Value>50.033</Value>
        </ProcessingTime>
      </PlannedEffort>
    </Job>
    <LayoutObject>
      <Identifier>LayoutObject:Conveyor_3</Identifier>
      <Description>Inline components. Straight conveyor.</Description>
      <Name>Conveyor_3</Name>
      <AssociatedResource>
        <ResourceIdentifier>Resource:Conveyor_3</ResourceIdentifier>
      </AssociatedResource>
      <Boundary>
        <Width>1507.544</Width>
        <Depth>376</Depth>
        <Height>700.1</Height>
        <Unit>millimeter</Unit>
        <CoordinateSystem>centerBased</CoordinateSystem>
      </Boundary>
      <Type>conveyor</Type>
      <Shape>
        <ShapeType>graphic</ShapeType>
        <Graphic>
          <GraphicType>modelGraphic</GraphicType>
          <FileName>\models\Conveyor_3.dae</FileName>
          <FileType>.dae</FileType>
          <Property>
            <Name>Up_Axis</Name>
            <Value>Z_UP</Value>
          </Property>
          <ModelUnit>millimeter</ModelUnit>
        </Graphic>
      </Shape>
    </LayoutObject>
    <Resource>
      <Identifier>Resource:Conveyor_3</Identifier>
      <Description>Conveyor_3</Description>
      <Property>
        <Name>PathCapacity</Name>
        <Value>9999</Value>
      </Property>
      <Property>
        <Name>ConveyorSpeed</Name>
        <Unit>millimeterPerSecond</Unit>
        <Value>30</Value>
      </Property>
      <Property>
        <Name>PathFrame_0</Name>
        <Description>Start</Description>
        <Unit>millimeter</Unit>
        <Value>0;1;0;0;-1;0;0;0;0;0;1;0;3446.089;-2509.245;700;1</Value>
      </Property>
      <Property>
        <Name>PathFrame_1</Name>
        <Description>End</Description>
        <Unit>millimeter</Unit>
        <Value>0;1;0;0;-1;0;0;0;0;0;1;0;3446.088;-1008.245;700;1</Value>
      </Property>
      <ResourceType>conveyor</ResourceType>
      <Name>Conveyor_3</Name>
      <CurrentStatus>busy</CurrentStatus>
    </Resource>
    <Job>
      <Identifier>Job1:Conveyor_3</Identifier>
      <Description>Conveyor_3</Description>
      <Status>released</Status>
      <PlannedEffort>
        <ResourcesRequired>
          <Resource>
            <ResourceIdentifier>Resource:Conveyor_3</ResourceIdentifier>
          </Resource>
        </ResourcesRequired>
        <SetupTime>
          <Unit>second</Unit>
          <Value>0</Value>
        </SetupTime>
        <ProcessingTime>
          <Unit>second</Unit>
          <Value>50.033</Value>
        </ProcessingTime>
      </PlannedEffort>
    </Job>
    <LayoutObject>
      <Identifier>LayoutObject:Conveyor</Identifier>
      <Description>Inline components. Straight conveyor.</Description>
      <Name>Conveyor</Name>
      <AssociatedResource>
        <ResourceIdentifier>Resource:Conveyor</ResourceIdentifier>
      </AssociatedResource>
      <Boundary>
        <Width>2001</Width>
        <Depth>376</Depth>
        <Height>700.1</Height>
        <Unit>millimeter</Unit>
        <CoordinateSystem>centerBased</CoordinateSystem>
      </Boundary>
      <Type>conveyor</Type>
      <Shape>
        <ShapeType>graphic</ShapeType>
        <Graphic>
          <GraphicType>modelGraphic</GraphicType>
          <FileName>\models\Conveyor.dae</FileName>
          <FileType>.dae</FileType>
          <Property>
            <Name>Up_Axis</Name>
            <Value>Z_UP</Value>
          </Property>
          <ModelUnit>millimeter</ModelUnit>
        </Graphic>
      </Shape>
    </LayoutObject>
    <Resource>
      <Identifier>Resource:Conveyor</Identifier>
      <Description>Conveyor</Description>
      <Property>
        <Name>PathCapacity</Name>
        <Value>9999</Value>
      </Property>
      <Property>
        <Name>ConveyorSpeed</Name>
        <Unit>millimeterPerSecond</Unit>
        <Value>30</Value>
      </Property>
      <Property>
        <Name>PathFrame_0</Name>
        <Description>Start</Description>
        <Unit>millimeter</Unit>
        <Value>1;0;0;0;0;1;0;0;0;0;1;0;0;0;700;1</Value>
      </Property>
      <Property>
        <Name>PathFrame_1</Name>
        <Description>End</Description>
        <Unit>millimeter</Unit>
        <Value>1;0;0;0;0;1;0;0;0;0;1;0;2001;0;700;1</Value>
      </Property>
      <ResourceType>conveyor</ResourceType>
      <Name>Conveyor</Name>
      <CurrentStatus>busy</CurrentStatus>
    </Resource>
    <Job>
      <Identifier>Job1:Conveyor</Identifier>
      <Description>Conveyor</Description>
      <Status>released</Status>
      <PlannedEffort>
        <ResourcesRequired>
          <Resource>
            <ResourceIdentifier>Resource:Conveyor</ResourceIdentifier>
          </Resource>
        </ResourcesRequired>
        <SetupTime>
          <Unit>second</Unit>
          <Value>0</Value>
        </SetupTime>
        <ProcessingTime>
          <Unit>second</Unit>
          <Value>66.7</Value>
        </ProcessingTime>
      </PlannedEffort>
    </Job>
    <LayoutObject>
      <Identifier>LayoutObject:Curve_Conveyor</Identifier>
      <Description>Inline components. Curved conveyor or spiral</Description>
      <Name>Curve_Conveyor</Name>
      <AssociatedResource>
        <ResourceIdentifier>Resource:Curve_Conveyor</ResourceIdentifier>
      </AssociatedResource>
      <Boundary>
        <Width>1175.215</Width>
        <Depth>1176.201</Depth>
        <Height>700.1</Height>
        <Unit>millimeter</Unit>
        <CoordinateSystem>centerBased</CoordinateSystem>
      </Boundary>
      <Type>conveyor</Type>
      <Shape>
        <ShapeType>graphic</ShapeType>
        <Graphic>
          <GraphicType>modelGraphic</GraphicType>
          <FileName>\models\Curve_Conveyor.dae</FileName>
          <FileType>.dae</FileType>
          <Property>
            <Name>Up_Axis</Name>
            <Value>Z_UP</Value>
          </Property>
          <ModelUnit>millimeter</ModelUnit>
        </Graphic>
      </Shape>
    </LayoutObject>
    <Resource>
      <Identifier>Resource:Curve_Conveyor</Identifier>
      <Description>Curve_Conveyor</Description>
      <Property>
        <Name>PathCapacity</Name>
        <Value>9999</Value>
      </Property>
      <Property>
        <Name>ConveyorSpeed</Name>
        <Unit>millimeterPerSecond</Unit>
        <Value>30</Value>
      </Property>
      <Property>
        <Name>PathFrame_0</Name>
        <Description>Start</Description>
        <Unit>millimeter</Unit>
        <Value>1;0;0;0;0;1;0;0;0;0;1;0;2001;0;700;1</Value>
      </Property>
      <Property>
        <Name>PathFrame_1</Name>
        <Description>frame_0</Description>
        <Unit>millimeter</Unit>
        <Value>1;0;0;0;0;1;0;0;0;0;1;0;2006;0;700;1</Value>
      </Property>
      <Property>
        <Name>PathFrame_2</Name>
        <Description>frame_1</Description>
        <Unit>millimeter</Unit>
        <Value>0.924;-0.383;0;0;0.383;0.924;0;0;0;0;1;0;2383.683;-76.12;700;1</Value>
      </Property>
      <Property>
        <Name>PathFrame_3</Name>
        <Description>frame_2</Description>
        <Unit>millimeter</Unit>
        <Value>0.707;-0.707;0;0;0.707;0.707;0;0;0;0;1;0;2708.107;-292.893;700;1</Value>
      </Property>
      <Property>
        <Name>PathFrame_4</Name>
        <Description>frame_3</Description>
        <Unit>millimeter</Unit>
        <Value>0.383;-0.924;0;0;0.924;0.383;0;0;0;0;1;0;2924.88;-617.317;700;1</Value>
      </Property>
      <Property>
        <Name>PathFrame_5</Name>
        <Description>frame_4</Description>
        <Unit>millimeter</Unit>
        <Value>0;-1;0;0;1;0;0;0;0;0;1;0;3001;-995;700;1</Value>
      </Property>
      <Property>
        <Name>PathFrame_6</Name>
        <Description>End</Description>
        <Unit>millimeter</Unit>
        <Value>0;-1;0;0;1;0;0;0;0;0;1;0;3001;-1000;700;1</Value>
      </Property>
      <ResourceType>conveyor</ResourceType>
      <Name>Curve_Conveyor</Name>
      <CurrentStatus>busy</CurrentStatus>
    </Resource>
    <Job>
      <Identifier>Job1:Curve_Conveyor</Identifier>
      <Description>Curve_Conveyor</Description>
      <Status>released</Status>
      <PlannedEffort>
        <ResourcesRequired>
          <Resource>
            <ResourceIdentifier>Resource:Curve_Conveyor</ResourceIdentifier>
          </Resource>
        </ResourcesRequired>
        <SetupTime>
          <Unit>second</Unit>
          <Value>0</Value>
        </SetupTime>
        <ProcessingTime>
          <Unit>second</Unit>
          <Value>52.031</Value>
        </ProcessingTime>
      </PlannedEffort>
    </Job>
    <LayoutObject>
      <Identifier>LayoutObject:Conveyor_2</Identifier>
      <Description>Inline components. Straight conveyor.</Description>
      <Name>Conveyor_2</Name>
      <AssociatedResource>
        <ResourceIdentifier>Resource:Conveyor_2</ResourceIdentifier>
      </AssociatedResource>
      <Boundary>
        <Width>1507.544</Width>
        <Depth>376</Depth>
        <Height>700.1</Height>
        <Unit>millimeter</Unit>
        <CoordinateSystem>centerBased</CoordinateSystem>
      </Boundary>
      <Type>conveyor</Type>
      <Shape>
        <ShapeType>graphic</ShapeType>
        <Graphic>
          <GraphicType>modelGraphic</GraphicType>
          <FileName>\models\Conveyor_2.dae</FileName>
          <FileType>.dae</FileType>
          <Property>
            <Name>Up_Axis</Name>
            <Value>Z_UP</Value>
          </Property>
          <ModelUnit>millimeter</ModelUnit>
        </Graphic>
      </Shape>
    </LayoutObject>
    <Resource>
      <Identifier>Resource:Conveyor_2</Identifier>
      <Description>Conveyor_2</Description>
      <Property>
        <Name>PathCapacity</Name>
        <Value>9999</Value>
      </Property>
      <Property>
        <Name>ConveyorSpeed</Name>
        <Unit>millimeterPerSecond</Unit>
        <Value>30</Value>
      </Property>
      <Property>
        <Name>PathFrame_0</Name>
        <Description>Start</Description>
        <Unit>millimeter</Unit>
        <Value>0;-1;0;0;1;0;0;0;0;0;1;0;3001;-1000;700;1</Value>
      </Property>
      <Property>
        <Name>PathFrame_1</Name>
        <Description>End</Description>
        <Unit>millimeter</Unit>
        <Value>0;-1;0;0;1;0;0;0;0;0;1;0;3001;-2501;700;1</Value>
      </Property>
      <ResourceType>conveyor</ResourceType>
      <Name>Conveyor_2</Name>
      <CurrentStatus>busy</CurrentStatus>
    </Resource>
    <Job>
      <Identifier>Job1:Conveyor_2</Identifier>
      <Description>Conveyor_2</Description>
      <Status>released</Status>
      <PlannedEffort>
        <ResourcesRequired>
          <Resource>
            <ResourceIdentifier>Resource:Conveyor_2</ResourceIdentifier>
          </Resource>
        </ResourcesRequired>
        <SetupTime>
          <Unit>second</Unit>
          <Value>0</Value>
        </SetupTime>
        <ProcessingTime>
          <Unit>second</Unit>
          <Value>50.033</Value>
        </ProcessingTime>
      </PlannedEffort>
    </Job>
    <LayoutObject>
      <Identifier>LayoutObject:Product_Feeder</Identifier>
      <Description>Product Creator</Description>
      <Name>Product_Feeder</Name>
      <AssociatedResource>
        <ResourceIdentifier>Resource:Product_Feeder</ResourceIdentifier>
      </AssociatedResource>
      <Boundary>
        <Width>300</Width>
        <Depth>500</Depth>
        <Height>705</Height>
        <Unit>millimeter</Unit>
        <CoordinateSystem>centerBased</CoordinateSystem>
      </Boundary>
      <Type>Feeder</Type>
      <Shape>
        <ShapeType>graphic</ShapeType>
        <Graphic>
          <GraphicType>modelGraphic</GraphicType>
          <FileName>\models\Product_Feeder.dae</FileName>
          <FileType>.dae</FileType>
          <Property>
            <Name>Up_Axis</Name>
            <Value>Z_UP</Value>
          </Property>
          <ModelUnit>millimeter</ModelUnit>
        </Graphic>
      </Shape>
    </LayoutObject>
    <Resource>
      <Identifier>Resource:Product_Feeder</Identifier>
      <Description>Product_Feeder</Description>
      <Property>
        <Name>FeedMode</Name>
        <Value>Single</Value>
      </Property>
      <Property>
        <Name>Interval</Name>
        <Unit>second</Unit>
        <Value>40</Value>
      </Property>
      <Property>
        <Name>CreationLimit</Name>
        <Value>100000</Value>
      </Property>
      <Property>
        <Name>PathCapacity</Name>
        <Value>999999</Value>
      </Property>
      <Property>
        <Name>ConveyorSpeed</Name>
        <Unit>millimeterPerSecond</Unit>
        <Value>30</Value>
      </Property>
      <Property>
        <Name>PathFrame_0</Name>
        <Description>CreateFrame</Description>
        <Unit>millimeter</Unit>
        <Value>1;0;0;0;0;1;0;0;0;0;1;0;-150;0;700;1</Value>
      </Property>
      <Property>
        <Name>PathFrame_1</Name>
        <Description>EndFrame</Description>
        <Unit>millimeter</Unit>
        <Value>1;0;0;0;0;1;0;0;0;0;1;0;0;0;700;1</Value>
      </Property>
      <ResourceType>Feeder</ResourceType>
      <Name>Product_Feeder</Name>
      <CurrentStatus>busy</CurrentStatus>
    </Resource>
    <Job>
      <Identifier>Job1:Product_Feeder</Identifier>
      <Description>Product_Feeder</Description>
      <Status>released</Status>
      <PlannedEffort>
        <PartsProduced>
          <PartInstance>
            <PartIdentifier>Part:45e69cfe-c2f2-4a25-8656-80da737035ff</PartIdentifier>
          </PartInstance>
        </PartsProduced>
        <ResourcesRequired>
          <Resource>
            <ResourceIdentifier>Resource:Product_Feeder</ResourceIdentifier>
          </Resource>
        </ResourcesRequired>
        <SetupTime>
          <Unit>second</Unit>
          <Value>0</Value>
        </SetupTime>
        <ProcessingTime>
          <Unit>second</Unit>
          <Value>5</Value>
        </ProcessingTime>
      </PlannedEffort>
    </Job>
    <LayoutObject>
      <Identifier>LayoutObject:From_Conveyor_Process</Identifier>
      <Description>Process Product Creator with flow interface</Description>
      <Name>From_Conveyor_Process</Name>
      <AssociatedResource>
        <ResourceIdentifier>Resource:From_Conveyor_Process</ResourceIdentifier>
      </AssociatedResource>
      <Boundary>
        <Width>186</Width>
        <Depth>600</Depth>
        <Height>705</Height>
        <Unit>millimeter</Unit>
        <CoordinateSystem>centerBased</CoordinateSystem>
      </Boundary>
      <Type>Feeder</Type>
      <Shape>
        <ShapeType>graphic</ShapeType>
        <Graphic>
          <GraphicType>modelGraphic</GraphicType>
          <FileName>\models\From_Conveyor_Process.dae</FileName>
          <FileType>.dae</FileType>
          <Property>
            <Name>Up_Axis</Name>
            <Value>Z_UP</Value>
          </Property>
          <ModelUnit>millimeter</ModelUnit>
        </Graphic>
      </Shape>
    </LayoutObject>
    <Resource>
      <Identifier>Resource:From_Conveyor_Process</Identifier>
      <Description>From_Conveyor_Process</Description>
      <Property>
        <Name>Capacity</Name>
        <Value>1</Value>
      </Property>
      <ResourceType>Feeder</ResourceType>
      <Name>From_Conveyor_Process</Name>
      <CurrentStatus>busy</CurrentStatus>
    </Resource>
    <Job>
      <Identifier>Job1:From_Conveyor_Process</Identifier>
      <Description>From_Conveyor_Process</Description>
      <Status>released</Status>
      <PlannedEffort>
        <ResourcesRequired>
          <Resource>
            <ResourceIdentifier>Resource:From_Conveyor_Process</ResourceIdentifier>
          </Resource>
        </ResourcesRequired>
        <SetupTime>
          <Unit>second</Unit>
          <Value>0</Value>
        </SetupTime>
        <ProcessingTime>
          <Unit>second</Unit>
          <Value>40</Value>
        </ProcessingTime>
        <ProcessPlan>
          <ProcessPlanIdentifier>Process:FromConveyor</ProcessPlanIdentifier>
        </ProcessPlan>
      </PlannedEffort>
    </Job>
    <LayoutObject>
      <Identifier>LayoutObject:To_Conveyor_Process</Identifier>
      <Description>Process Product Creator with flow interface</Description>
      <Name>To_Conveyor_Process</Name>
      <AssociatedResource>
        <ResourceIdentifier>Resource:To_Conveyor_Process</ResourceIdentifier>
      </AssociatedResource>
      <Boundary>
        <Width>186</Width>
        <Depth>600</Depth>
        <Height>705</Height>
        <Unit>millimeter</Unit>
        <CoordinateSystem>centerBased</CoordinateSystem>
      </Boundary>
      <Type>Feeder</Type>
      <Shape>
        <ShapeType>graphic</ShapeType>
        <Graphic>
          <GraphicType>modelGraphic</GraphicType>
          <FileName>\models\To_Conveyor_Process.dae</FileName>
          <FileType>.dae</FileType>
          <Property>
            <Name>Up_Axis</Name>
            <Value>Z_UP</Value>
          </Property>
          <ModelUnit>millimeter</ModelUnit>
        </Graphic>
      </Shape>
    </LayoutObject>
    <Resource>
      <Identifier>Resource:To_Conveyor_Process</Identifier>
      <Description>To_Conveyor_Process</Description>
      <Property>
        <Name>Capacity</Name>
        <Value>1</Value>
      </Property>
      <ResourceType>Feeder</ResourceType>
      <Name>To_Conveyor_Process</Name>
      <CurrentStatus>busy</CurrentStatus>
    </Resource>
    <Job>
      <Identifier>Job1:To_Conveyor_Process</Identifier>
      <Description>To_Conveyor_Process</Description>
      <Status>released</Status>
      <PlannedEffort>
        <ResourcesRequired>
          <Resource>
            <ResourceIdentifier>Resource:To_Conveyor_Process</ResourceIdentifier>
          </Resource>
        </ResourcesRequired>
        <SetupTime>
          <Unit>second</Unit>
          <Value>0</Value>
        </SetupTime>
        <ProcessingTime>
          <Unit>second</Unit>
          <Value>40</Value>
        </ProcessingTime>
        <ProcessPlan>
          <ProcessPlanIdentifier>Process:ToConveyor</ProcessPlanIdentifier>
        </ProcessPlan>
      </PlannedEffort>
    </Job>
    <LayoutObject>
      <Identifier>LayoutObject:RobotController</Identifier>
      <Description>Call robot to do works tasks using this pedestal component. Connect a servo track between the controller and robot to enable automatic servo-track motions.</Description>
      <Name>RobotController</Name>
      <AssociatedResource>
        <ResourceIdentifier>Resource:RobotController</ResourceIdentifier>
      </AssociatedResource>
      <Boundary>
        <Width>1648.2</Width>
        <Depth>1000</Depth>
        <Height>1639.677</Height>
        <Unit>millimeter</Unit>
        <CoordinateSystem>centerBased</CoordinateSystem>
      </Boundary>
      <Type>other</Type>
      <Shape>
        <ShapeType>graphic</ShapeType>
        <Graphic>
          <GraphicType>modelGraphic</GraphicType>
          <FileName>\models\RobotController.dae</FileName>
          <FileType>.dae</FileType>
          <Property>
            <Name>Up_Axis</Name>
            <Value>Z_UP</Value>
          </Property>
          <ModelUnit>millimeter</ModelUnit>
        </Graphic>
      </Shape>
    </LayoutObject>
    <Resource>
      <Identifier>Resource:RobotController</Identifier>
      <Description>RobotController</Description>
      <ResourceType>other</ResourceType>
      <Name>RobotController</Name>
      <CurrentStatus>busy</CurrentStatus>
    </Resource>
    <LayoutObject>
      <Identifier>LayoutObject:EH320</Identifier>
      <Description>Horizontal Machining Center</Description>
      <Name>EH320</Name>
      <AssociatedResource>
        <ResourceIdentifier>Resource:EH320</ResourceIdentifier>
      </AssociatedResource>
      <Boundary>
        <Width>1739.529</Width>
        <Depth>3411.911</Depth>
        <Height>2337.1</Height>
        <Unit>millimeter</Unit>
        <CoordinateSystem>centerBased</CoordinateSystem>
      </Boundary>
      <Type>machine</Type>
      <Shape>
        <ShapeType>graphic</ShapeType>
        <Graphic>
          <GraphicType>modelGraphic</GraphicType>
          <FileName>\models\EH320.dae</FileName>
          <FileType>.dae</FileType>
          <Property>
            <Name>Up_Axis</Name>
            <Value>Z_UP</Value>
          </Property>
          <ModelUnit>millimeter</ModelUnit>
        </Graphic>
      </Shape>
    </LayoutObject>
    <Resource>
      <Identifier>Resource:EH320</Identifier>
      <Description>EH320</Description>
      <Property>
        <Name>Capacity</Name>
        <Value>1</Value>
      </Property>
      <Property>
        <Name>MTBF</Name>
        <Unit>second</Unit>
        <Value>0</Value>
      </Property>
      <Property>
        <Name>MTTR</Name>
        <Unit>second</Unit>
        <Value>0</Value>
      </Property>
      <ResourceType>machine</ResourceType>
      <Name>EH320</Name>
      <CurrentStatus>busy</CurrentStatus>
    </Resource>
    <Job>
      <Identifier>Job1:EH320</Identifier>
      <Description>EH320</Description>
      <Status>released</Status>
      <PlannedEffort>
        <ResourcesRequired>
          <Resource>
            <ResourceIdentifier>Resource:EH320</ResourceIdentifier>
          </Resource>
        </ResourcesRequired>
        <SetupTime>
          <Unit>second</Unit>
          <Value>4</Value>
        </SetupTime>
        <ProcessingTime>
          <Unit>second</Unit>
          <Value>40</Value>
        </ProcessingTime>
        <ProcessPlan>
          <ProcessPlanIdentifier>Process:EH320</ProcessPlanIdentifier>
        </ProcessPlan>
      </PlannedEffort>
    </Job>
    <Part>
      <Identifier>Part:6deb6724-2ce2-483d-8c45-34e0dfa4615a</Identifier>
      <Description>FinalProduct</Description>
      <Property>
        <Name>FilePath</Name>
        <Value>\models\block_geo.dae</Value>
      </Property>
      <Property>
        <Name>Up_Axis</Name>
        <Value>Z_Up</Value>
      </Property>
      <Property>
        <Name>ModelUnit</Name>
        <Value>millimeter</Value>
      </Property>
      <Property>
        <Name>Color</Name>
        <Value>green</Value>
      </Property>
      <PartType>
        <PartTypeIdentifier>PartType:6deb6724-2ce2-483d-8c45-34e0dfa4615a</PartTypeIdentifier>
      </PartType>
      <Name>FinalProduct</Name>
      <ProductionStatus>unknown</ProductionStatus>
      <Location>
        <WithinFacilityLocation>1;0;0;0;0;1;0;0;0;0;1;0;0;0;0;1</WithinFacilityLocation>
      </Location>
      <Size>
        <Unit>millimeter</Unit>
        <Width>160</Width>
        <Depth>160</Depth>
        <Height>100</Height>
      </Size>
    </Part>
    <PartType>
      <Identifier>PartType:6deb6724-2ce2-483d-8c45-34e0dfa4615a</Identifier>
      <Description>FinalProduct</Description>
      <Name>FinalProduct</Name>
    </PartType>
    <Part>
      <Identifier>Part:45e69cfe-c2f2-4a25-8656-80da737035ff</Identifier>
      <Description>RawMaterial</Description>
      <Property>
        <Name>FilePath</Name>
        <Value>\models\cylinder.dae</Value>
      </Property>
      <Property>
        <Name>Up_Axis</Name>
        <Value>Z_Up</Value>
      </Property>
      <Property>
        <Name>ModelUnit</Name>
        <Value>millimeter</Value>
      </Property>
      <Property>
        <Name>Color</Name>
        <Value>yellow</Value>
      </Property>
      <Property>
        <Name>SKU</Name>
        <Value>S12T-Cyl-RS</Value>
      </Property>
      <PartType>
        <PartTypeIdentifier>PartType:45e69cfe-c2f2-4a25-8656-80da737035ff</PartTypeIdentifier>
      </PartType>
      <Name>RawMaterial</Name>
      <ProductionStatus>unknown</ProductionStatus>
      <Location>
        <WithinFacilityLocation>1;0;0;0;0;1;0;0;0;0;1;0;0;0;0;1</WithinFacilityLocation>
      </Location>
      <Size>
        <Unit>millimeter</Unit>
        <Width>240</Width>
        <Depth>240</Depth>
        <Height>150</Height>
      </Size>
    </Part>
    <PartType>
      <Identifier>PartType:45e69cfe-c2f2-4a25-8656-80da737035ff</Identifier>
      <Description>RawMaterial</Description>
      <Name>RawMaterial</Name>
    </PartType>
    <Job>
      <Identifier>Job1:Transport:EH320-To_Conveyor_Process</Identifier>
      <Description>Transport:EH320-To_Conveyor_Process</Description>
      <Status>released</Status>
      <PlannedEffort>
        <PartsProduced>
          <PartInstance>
            <PartIdentifier>Part:6deb6724-2ce2-483d-8c45-34e0dfa4615a</PartIdentifier>
          </PartInstance>
        </PartsProduced>
        <PartsConsumed>
          <PartInstance>
            <PartIdentifier>Part:6deb6724-2ce2-483d-8c45-34e0dfa4615a</PartIdentifier>
          </PartInstance>
        </PartsConsumed>
        <ResourcesRequired>
          <Resource>
            <ResourceIdentifier>Resource:RobotController</ResourceIdentifier>
          </Resource>
        </ResourcesRequired>
        <SetupTime>
          <Unit>second</Unit>
          <Value>0</Value>
        </SetupTime>
        <ProcessingTime>
          <Unit>second</Unit>
          <Value>4</Value>
        </ProcessingTime>
      </PlannedEffort>
    </Job>
    <Job>
      <Identifier>Job1:Transport:From_Conveyor_Process-EH320</Identifier>
      <Description>Transport:From_Conveyor_Process-EH320</Description>
      <Status>released</Status>
      <PlannedEffort>
        <PartsProduced>
          <PartInstance>
            <PartIdentifier>Part:6deb6724-2ce2-483d-8c45-34e0dfa4615a</PartIdentifier>
          </PartInstance>
        </PartsProduced>
        <PartsConsumed>
          <PartInstance>
            <PartIdentifier>Part:6deb6724-2ce2-483d-8c45-34e0dfa4615a</PartIdentifier>
          </PartInstance>
        </PartsConsumed>
        <ResourcesRequired>
          <Resource>
            <ResourceIdentifier>Resource:RobotController</ResourceIdentifier>
          </Resource>
        </ResourcesRequired>
        <SetupTime>
          <Unit>second</Unit>
          <Value>0</Value>
        </SetupTime>
        <ProcessingTime>
          <Unit>second</Unit>
          <Value>4</Value>
        </ProcessingTime>
      </PlannedEffort>
    </Job>
    <ProcessPlan>
      <Identifier>Process:FromConveyor</Identifier>
      <Description>Process:FromConveyor</Description>
      <ResourcesRequired>
        <Resource>
          <ResourceIdentifier>Resource:From_Conveyor_Process</ResourceIdentifier>
        </Resource>
      </ResourcesRequired>
      <FirstProcess>
        <ProcessIdentifier>Process:FromConveyor:MainProcess</ProcessIdentifier>
      </FirstProcess>
      <Process>
        <Identifier>Process:FromConveyor:MainProcess</Identifier>
        <Description>Process:FromConveyor:MainProcess</Description>
        <SetupTime>
          <Unit>second</Unit>
          <Value>0</Value>
        </SetupTime>
        <OperationTime>
          <Unit>second</Unit>
          <Value>40</Value>
        </OperationTime>
        <RepetitionCount>1</RepetitionCount>
        <SubProcessGroup>
          <Type>sequence</Type>
          <Process>
            <ProcessIdentifier>Process:FromConveyor:Statement-0</ProcessIdentifier>
          </Process>
          <Process>
            <ProcessIdentifier>Process:FromConveyor:Statement-1</ProcessIdentifier>
          </Process>
        </SubProcessGroup>
      </Process>
      <Process>
        <Identifier>Process:FromConveyor:Statement-0</Identifier>
        <Description>ITransportInStatement</Description>
        <ResourcesRequired>
          <Resource>
            <ResourceIdentifier>Resource:From_Conveyor_Process</ResourceIdentifier>
          </Resource>
        </ResourcesRequired>
        <SetupTime>
          <Unit>second</Unit>
          <Value>0</Value>
        </SetupTime>
        <OperationTime>
          <Unit>second</Unit>
          <Value>38.304</Value>
        </OperationTime>
      </Process>
      <Process>
        <Identifier>Process:FromConveyor:Statement-1</Identifier>
        <Description>ITransportOutStatement</Description>
        <ResourcesRequired>
          <Resource>
            <ResourceIdentifier>Resource:From_Conveyor_Process</ResourceIdentifier>
          </Resource>
        </ResourcesRequired>
        <SetupTime>
          <Unit>second</Unit>
          <Value>0</Value>
        </SetupTime>
        <OperationTime>
          <Unit>second</Unit>
          <Value>1.696</Value>
        </OperationTime>
      </Process>
    </ProcessPlan>
    <ProcessPlan>
      <Identifier>Process:ToConveyor</Identifier>
      <Description>Process:ToConveyor</Description>
      <ResourcesRequired>
        <Resource>
          <ResourceIdentifier>Resource:To_Conveyor_Process</ResourceIdentifier>
        </Resource>
      </ResourcesRequired>
      <FirstProcess>
        <ProcessIdentifier>Process:ToConveyor:MainProcess</ProcessIdentifier>
      </FirstProcess>
      <Process>
        <Identifier>Process:ToConveyor:MainProcess</Identifier>
        <Description>Process:ToConveyor:MainProcess</Description>
        <SetupTime>
          <Unit>second</Unit>
          <Value>0</Value>
        </SetupTime>
        <OperationTime>
          <Unit>second</Unit>
          <Value>40</Value>
        </OperationTime>
        <RepetitionCount>1</RepetitionCount>
        <SubProcessGroup>
          <Type>sequence</Type>
          <Process>
            <ProcessIdentifier>Process:ToConveyor:Statement-0</ProcessIdentifier>
          </Process>
          <Process>
            <ProcessIdentifier>Process:ToConveyor:Statement-1</ProcessIdentifier>
          </Process>
        </SubProcessGroup>
      </Process>
      <Process>
        <Identifier>Process:ToConveyor:Statement-0</Identifier>
        <Description>ITransportInStatement</Description>
        <ResourcesRequired>
          <Resource>
            <ResourceIdentifier>Resource:To_Conveyor_Process</ResourceIdentifier>
          </Resource>
        </ResourcesRequired>
        <SetupTime>
          <Unit>second</Unit>
          <Value>0</Value>
        </SetupTime>
        <OperationTime>
          <Unit>second</Unit>
          <Value>40</Value>
        </OperationTime>
      </Process>
      <Process>
        <Identifier>Process:ToConveyor:Statement-1</Identifier>
        <Description>ITransportOutStatement</Description>
        <ResourcesRequired>
          <Resource>
            <ResourceIdentifier>Resource:To_Conveyor_Process</ResourceIdentifier>
          </Resource>
        </ResourcesRequired>
        <SetupTime>
          <Unit>second</Unit>
          <Value>0</Value>
        </SetupTime>
        <OperationTime>
          <Unit>second</Unit>
          <Value>0</Value>
        </OperationTime>
      </Process>
    </ProcessPlan>
    <ProcessPlan>
      <Identifier>Process:EH320</Identifier>
      <Description>Process:EH320</Description>
      <ResourcesRequired>
        <Resource>
          <ResourceIdentifier>Resource:EH320</ResourceIdentifier>
        </Resource>
      </ResourcesRequired>
      <FirstProcess>
        <ProcessIdentifier>Process:EH320:MainProcess</ProcessIdentifier>
      </FirstProcess>
      <Process>
        <Identifier>Process:EH320:MainProcess</Identifier>
        <Description>Process:EH320:MainProcess</Description>
        <SetupTime>
          <Unit>second</Unit>
          <Value>0</Value>
        </SetupTime>
        <OperationTime>
          <Unit>second</Unit>
          <Value>40</Value>
        </OperationTime>
        <RepetitionCount>1</RepetitionCount>
        <SubProcessGroup>
          <Type>sequence</Type>
          <Process>
            <ProcessIdentifier>Process:EH320:Statement-0</ProcessIdentifier>
          </Process>
          <Process>
            <ProcessIdentifier>Process:EH320:Statement-1</ProcessIdentifier>
          </Process>
          <Process>
            <ProcessIdentifier>Process:EH320:Statement-2</ProcessIdentifier>
          </Process>
          <Process>
            <ProcessIdentifier>Process:EH320:Statement-3</ProcessIdentifier>
          </Process>
          <Process>
            <ProcessIdentifier>Process:EH320:Statement-4</ProcessIdentifier>
          </Process>
          <Process>
            <ProcessIdentifier>Process:EH320:Statement-Machine_Process5</ProcessIdentifier>
          </Process>
          <Process>
            <ProcessIdentifier>Process:EH320:Statement-6</ProcessIdentifier>
          </Process>
          <Process>
            <ProcessIdentifier>Process:EH320:Statement-7</ProcessIdentifier>
          </Process>
          <Process>
            <ProcessIdentifier>Process:EH320:Statement-8</ProcessIdentifier>
          </Process>
          <Process>
            <ProcessIdentifier>Process:EH320:Statement-9</ProcessIdentifier>
          </Process>
        </SubProcessGroup>
      </Process>
      <Process>
        <Identifier>Process:EH320:Statement-0</Identifier>
        <Description>ISetStatisticsStateStatement</Description>
        <ResourcesRequired>
          <Resource>
            <ResourceIdentifier>Resource:EH320</ResourceIdentifier>
          </Resource>
        </ResourcesRequired>
        <SetupTime>
          <Unit>second</Unit>
          <Value>0</Value>
        </SetupTime>
        <OperationTime>
          <Unit>second</Unit>
          <Value>0</Value>
        </OperationTime>
      </Process>
      <Process>
        <Identifier>Process:EH320:Statement-1</Identifier>
        <Description>ITransportInStatement</Description>
        <ResourcesRequired>
          <Resource>
            <ResourceIdentifier>Resource:EH320</ResourceIdentifier>
          </Resource>
        </ResourcesRequired>
        <SetupTime>
          <Unit>second</Unit>
          <Value>0</Value>
        </SetupTime>
        <OperationTime>
          <Unit>second</Unit>
          <Value>19.363</Value>
        </OperationTime>
      </Process>
      <Process>
        <Identifier>Process:EH320:Statement-2</Identifier>
        <Description>ISetStatisticsStateStatement</Description>
        <ResourcesRequired>
          <Resource>
            <ResourceIdentifier>Resource:EH320</ResourceIdentifier>
          </Resource>
        </ResourcesRequired>
        <SetupTime>
          <Unit>second</Unit>
          <Value>0</Value>
        </SetupTime>
        <OperationTime>
          <Unit>second</Unit>
          <Value>0</Value>
        </OperationTime>
      </Process>
      <Process>
        <Identifier>Process:EH320:Statement-3</Identifier>
        <Description>IProcessDelayStatement</Description>
        <ResourcesRequired>
          <Resource>
            <ResourceIdentifier>Resource:EH320</ResourceIdentifier>
          </Resource>
        </ResourcesRequired>
        <SetupTime>
          <Unit>second</Unit>
          <Value>0</Value>
        </SetupTime>
        <OperationTime>
          <Unit>second</Unit>
          <Value>1</Value>
        </OperationTime>
      </Process>
      <Process>
        <Identifier>Process:EH320:Statement-4</Identifier>
        <Description>IMoveJointStatement</Description>
        <ResourcesRequired>
          <Resource>
            <ResourceIdentifier>Resource:EH320</ResourceIdentifier>
          </Resource>
        </ResourcesRequired>
        <SetupTime>
          <Unit>second</Unit>
          <Value>0</Value>
        </SetupTime>
        <OperationTime>
          <Unit>second</Unit>
          <Value>4</Value>
        </OperationTime>
      </Process>
      <Process>
        <Identifier>Process:EH320:Statement-Machine_Process5</Identifier>
        <Description>IProcessStatement</Description>
        <ResourcesRequired>
          <Resource>
            <ResourceIdentifier>Resource:EH320</ResourceIdentifier>
          </Resource>
        </ResourcesRequired>
        <SetupTime>
          <Unit>second</Unit>
          <Value>0</Value>
        </SetupTime>
        <OperationTime>
          <Unit>second</Unit>
          <Value>10</Value>
        </OperationTime>
      </Process>
      <Process>
        <Identifier>Process:EH320:Statement-6</Identifier>
        <Description>IChangeProductTypeStatement</Description>
        <PartsProduced>
          <PartInstance>
            <PartIdentifier>Part:6deb6724-2ce2-483d-8c45-34e0dfa4615a</PartIdentifier>
          </PartInstance>
        </PartsProduced>
        <ResourcesRequired>
          <Resource>
            <ResourceIdentifier>Resource:EH320</ResourceIdentifier>
          </Resource>
        </ResourcesRequired>
        <SetupTime>
          <Unit>second</Unit>
          <Value>0</Value>
        </SetupTime>
        <OperationTime>
          <Unit>second</Unit>
          <Value>0</Value>
        </OperationTime>
      </Process>
      <Process>
        <Identifier>Process:EH320:Statement-7</Identifier>
        <Description>IMoveJointStatement</Description>
        <ResourcesRequired>
          <Resource>
            <ResourceIdentifier>Resource:EH320</ResourceIdentifier>
          </Resource>
        </ResourcesRequired>
        <SetupTime>
          <Unit>second</Unit>
          <Value>0</Value>
        </SetupTime>
        <OperationTime>
          <Unit>second</Unit>
          <Value>4</Value>
        </OperationTime>
      </Process>
      <Process>
        <Identifier>Process:EH320:Statement-8</Identifier>
        <Description>ISetStatisticsStateStatement</Description>
        <ResourcesRequired>
          <Resource>
            <ResourceIdentifier>Resource:EH320</ResourceIdentifier>
          </Resource>
        </ResourcesRequired>
        <SetupTime>
          <Unit>second</Unit>
          <Value>0</Value>
        </SetupTime>
        <OperationTime>
          <Unit>second</Unit>
          <Value>0</Value>
        </OperationTime>
      </Process>
      <Process>
        <Identifier>Process:EH320:Statement-9</Identifier>
        <Description>ITransportOutStatement</Description>
        <ResourcesRequired>
          <Resource>
            <ResourceIdentifier>Resource:EH320</ResourceIdentifier>
          </Resource>
        </ResourcesRequired>
        <SetupTime>
          <Unit>second</Unit>
          <Value>0</Value>
        </SetupTime>
        <OperationTime>
          <Unit>second</Unit>
          <Value>1.637</Value>
        </OperationTime>
      </Process>
    </ProcessPlan>
  </DataSection>
</CMSDDocument>